setup.py
wheelshop/__init__.py
wheelshop/app.py
wheelshop.egg-info/PKG-INFO
wheelshop.egg-info/SOURCES.txt
wheelshop.egg-info/dependency_links.txt
wheelshop.egg-info/not-zip-safe
wheelshop.egg-info/requires.txt
wheelshop.egg-info/top_level.txt