Metadata-Version: 1.0
Name: wheelshop
Version: 0.1
Summary:  your python wheels on a PyPI compatible server using flask and S3
Home-page: UNKNOWN
Author: Kristian Øllegaard
Author-email: kristian@livesystems.info
License: UNKNOWN
Platform: UNKNOWN
